onepassword_tools/__init__.py
onepassword_tools/__main__.py
onepassword_tools/__version__.py
onepassword_tools/lib/ClickUtils.py
onepassword_tools/lib/ConfigFile.py
onepassword_tools/lib/Crypto.py
onepassword_tools/lib/Log.py
onepassword_tools/lib/MiscUtils.py
onepassword_tools/lib/NewItemCommand.py
onepassword_tools/lib/OnePasswordDatabaseItem.py
onepassword_tools/lib/OnePasswordItem.py
onepassword_tools/lib/OnePasswordLoginItem.py
onepassword_tools/lib/OnePasswordResult.py
onepassword_tools/lib/OnePasswordSSHKeyItem.py
onepassword_tools/lib/OnePasswordServerItem.py
onepassword_tools/lib/OnePasswordUtils.py
onepassword_tools/lib/__init__.py
onepassword_tools/new_database_account/__init__.py
onepassword_tools/new_database_account/new_database_account.py
onepassword_tools/new_server_account/__init__.py
onepassword_tools/new_server_account/new_server_account.py
onepassword_tools/new_ssh_key/__init__.py
onepassword_tools/new_ssh_key/new_ssh_key.py
onepassword_tools/new_website_account/__init__.py
onepassword_tools/new_website_account/new_website_account.py
onepassword_tools/ssh_add/__init__.py
onepassword_tools/ssh_add/ssh_add.py
onepassword_tools-1.6.0.dist-info/LICENSE
onepassword_tools-1.6.0.dist-info/METADATA
onepassword_tools-1.6.0.dist-info/WHEEL
onepassword_tools-1.6.0.dist-info/entry_points.txt
onepassword_tools-1.6.0.dist-info/top_level.txt
onepassword_tools-1.6.0.dist-info/RECORD
