Metadata-Version: 2.1
Name: onepassword-tools
Version: 1.6.0
Summary: This is a collection of 1Password related CLI tools and helpers
Home-page: https://github.com/mickaelperrin/onepassword-tools
Author: Mickaël Perrin
Author-email: dev@mickaelperrin.fr
License: GPLv3
Keywords: onepassword 1password cli password secrets tools
Classifier: License :: OSI Approved :: GNU General Public License v3 or later (GPLv3+)
Classifier: Development Status :: 4 - Beta
Classifier: Environment :: Console
Classifier: Intended Audience :: Information Technology
Classifier: Natural Language :: French
Classifier: Topic :: Security
Classifier: Topic :: Security :: Cryptography
Classifier: Topic :: Utilities
Classifier: Programming Language :: Python
Classifier: Programming Language :: Python :: 3
Classifier: Programming Language :: Python :: 3.7
Classifier: Programming Language :: Python :: Implementation :: CPython
Classifier: Programming Language :: Python :: Implementation :: PyPy
Requires-Python: >=3.7.0
License-File: LICENSE
Requires-Dist: onepassword-local-search (>=1.1.3)
Requires-Dist: click (==8.0.3)
Requires-Dist: click-log (==0.3.2)
Requires-Dist: PyYAML (==6.0)
Requires-Dist: pexpect (==4.8.0)
Requires-Dist: plumbum (==1.7.2)
Requires-Dist: inquirer (==2.9.1)
